lignator/__init__.py
lignator/__main__.py
lignator/cli.py
lignator/commands/__init__.py
lignator/commands/headers.py
lignator/commands/process.py
lignator/data_table.py
lignator/logger.py
lignator-1.0.0.dist-info/METADATA
lignator-1.0.0.dist-info/WHEEL
lignator-1.0.0.dist-info/entry_points.txt
lignator-1.0.0.dist-info/RECORD
