Metadata-Version: 2.1
Name: lignator
Version: 1.0.0
Summary: 
License: MIT
Author: Carlos Beltran Recabarren
Author-email: cbrecabarren@gmail.com
Requires-Python: >=3.12,<4.0
Classifier: License :: OSI Approved :: MIT License
Classifier: Programming Language :: Python :: 3
Classifier: Programming Language :: Python :: 3.12
Requires-Dist: inflection (>=0.5.1,<0.6.0)
Requires-Dist: numpy (>=1.26.4,<2.0.0)
Requires-Dist: pandas (>=2.2.2,<3.0.0)
Requires-Dist: python-dotenv (>=1.0.1,<2.0.0)
